{"scan_name":"tika-core-1.13","scan_version":"","repo_url":"","scan_timestamp":"2020-07-27T07:38:22.172Z","scan_buildCreationInfo":{"rootDir":"C:\\Users\\Guanqing\\Documents\\huawei_pom\\tika-core-1.13","repo_name":"","build_time":"","commit_sha":"","branch":"","repo_url":"","SBD_version":"2020/03/17"},"scan_filesOfInterest":[],"projects":[{"artifact_id":"tika-core","group_id":"org.apache.tika","version":"1.13","level":0,"type":"user_module","package_manager":{"package_manager":"Maven","language":"Java","working_dir":"C:\\Users\\Guanqing\\Documents\\huawei_pom\\tika-core-1.13","running_mode":"airgap","characteristic_files":[{"file_name":"pom.xml","file_path":"pom.xml"}]},"dependencies":[{"artifact_id":"org.osgi.core","group_id":"org.osgi","version":"4.0.0","level":1,"type":"dependency","dependencies":[]},{"artifact_id":"org.osgi.compendium","group_id":"org.osgi","version":"4.0.0","level":1,"type":"dependency","dependencies":[]},{"artifact_id":"bndlib","group_id":"biz.aQute","version":"","level":1,"type":"dependency","dependencies":[]},{"artifact_id":"junit","group_id":"junit","version":"","level":1,"type":"dependency","dependencies":[]}]}]}